HumanTone/__init__.py
HumanTone/paraphrase.py
HumanTone/sentiment.py
HumanTone/similarity.py
HumanTone/speech.py
humantone-0.1.5.dist-info/METADATA
humantone-0.1.5.dist-info/WHEEL
humantone-0.1.5.dist-info/top_level.txt
humantone-0.1.5.dist-info/RECORD
