Metadata-Version: 2.4
Name: HumanTone
Version: 0.1.5
Summary: A unique sentiment analysis library with paraphrasing, contextual similarity, and speech output.
Author: Vansh Gautam
Author-email: vanshgautam2005@gmail.com
Classifier: Programming Language :: Python :: 3
Classifier: License :: OSI Approved :: MIT License
Classifier: Operating System :: OS Independent
Requires-Python: >=3.7
Requires-Dist: transformers
Requires-Dist: textblob
Requires-Dist: nltk
Requires-Dist: sentence-transformers
Requires-Dist: pyttsx3
Requires-Dist: torch
Requires-Dist: scipy
Requires-Dist: pandas
Dynamic: author
Dynamic: author-email
Dynamic: classifier
Dynamic: description
Dynamic: description-content-type
Dynamic: requires-dist
Dynamic: requires-python
Dynamic: summary
